thagomizer/__init__.py
thagomizer/_version.py
thagomizer/utils.py
thagomizer/video.py
thagomizer-0.5.6.dist-info/METADATA
thagomizer-0.5.6.dist-info/WHEEL
thagomizer-0.5.6.dist-info/RECORD
