Metadata-Version: 2.4
Name: thagomizer
Version: 0.5.6
Summary: A collection of useful tools in python.
Author-email: Srinivas Gorur-Shandilya <code@srinivas.gs>
Requires-Python: >=3.10
Requires-Dist: beartype>=0.19.0
Requires-Dist: xxhash>=3.5.0
